textmeld/__init__.py
textmeld/cli.py
textmeld/textmeld.py
textmeld-0.3.0.dist-info/LICENSE
textmeld-0.3.0.dist-info/METADATA
textmeld-0.3.0.dist-info/WHEEL
textmeld-0.3.0.dist-info/entry_points.txt
textmeld-0.3.0.dist-info/RECORD
