Metadata-Version: 2.3
Name: textmeld
Version: 0.3.0
Summary: A tool to combine multiple text files into one for LLM training and prompts
Author: Hamham Taro
Author-email: hamhamtarotottoko@gmail.com
Requires-Python: >=3.10,<4.0
Classifier: Programming Language :: Python :: 3
Classifier: Programming Language :: Python :: 3.10
Classifier: Programming Language :: Python :: 3.11
Classifier: Programming Language :: Python :: 3.12
Classifier: Programming Language :: Python :: 3.13
